LICENSE
README.md
setup.py
raymarching/__init__.py
raymarching/raymarching.frag
raymarching/raymarching.py
raymarching.egg-info/PKG-INFO
raymarching.egg-info/SOURCES.txt
raymarching.egg-info/dependency_links.txt
raymarching.egg-info/top_level.txt