Metadata-Version: 2.1
Name: raymarching
Version: 0.1.1
Summary: Module for ray marching GLSL fragment shaders generation.
Home-page: https://github.com/NamorNiradnug/raymarching
Author: NamorNiradnug
Author-email: roma57linux@gmail.com
License: MIT
Project-URL: Bug Tracker, https://github.com/NamorNiradnug/raymarching/issues
Project-URL: Source, https://github.com/NamorNiradnug/raymarching
Platform: UNKNOWN
Classifier: Programming Language :: Python :: 3
Classifier: License :: OSI Approved :: MIT License
Classifier: Operating System :: OS Independent
Requires-Python: >=3.7
License-File: LICENSE
